{
  "data-center-glycol-cooling": {
    "status": "published",
    "target_platforms": [
      "x",
      "telegram",
      "linkedin_specsheet"
    ],
    "published_at": "2026-06-30T00:00:00+08:00"
  },
  "data-center-energy-efficiency": {
    "status": "published",
    "target_platforms": [
      "x",
      "telegram",
      "linkedin_specsheet"
    ],
    "published_at": "2026-07-02T00:00:00+08:00"
  },
  "ai-building-energy-management": {
    "status": "published",
    "target_platforms": [
      "x",
      "telegram",
      "linkedin_specsheet"
    ],
    "published_at": "2026-07-06T00:00:00+08:00"
  },
  "iaq-monitoring-commercial-buildings": {
    "status": "published",
    "target_platforms": [
      "x",
      "telegram",
      "linkedin_specsheet"
    ],
    "published_at": "2026-07-24T00:00:00+08:00",
    "source": "Northstar Jul 16"
  },
  "energy-efficiency-building-codes-asia": {
    "status": "published",
    "target_platforms": [
      "x",
      "telegram",
      "linkedin_specsheet"
    ],
    "published_at": "2026-07-24T00:00:00+08:00",
    "source": "Northstar Jul 23"
  },
  "air-side-vav-damper-selection": {
    "status": "published",
    "target_platforms": [
      "x",
      "telegram",
      "linkedin_specsheet"
    ],
    "published_at": "2026-07-24T00:00:00+08:00",
    "source": "Northstar Jul 24 — Air-side"
  },
  "water-side-control-valve-selection": {
    "status": "published",
    "target_platforms": [
      "x",
      "telegram",
      "linkedin_specsheet"
    ],
    "published_at": "2026-07-24T00:00:00+08:00",
    "source": "Northstar Jul 24 — Water-side"
  },
  "building-controls-bms-integration": {
    "status": "published",
    "target_platforms": [
      "x",
      "telegram",
      "linkedin_specsheet"
    ],
    "published_at": "2026-07-24T00:00:00+08:00",
    "source": "Northstar Jul 24 — Controls"
  }
}
